optimize_device_analysis/__init__.py
optimize_device_analysis/cpu_metrics.py
optimize_device_analysis/memory_metrics.py
optimize_device_analysis/network_metrics.py
optimize_device_analysis/os_specific/__init__.py
optimize_device_analysis/os_specific/linux_metrics.py
optimize_device_analysis/os_specific/macos_metrics.py
optimize_device_analysis/os_specific/windows_metrics.py
optimize_device_analysis-0.1.3.dist-info/METADATA
optimize_device_analysis-0.1.3.dist-info/WHEEL
optimize_device_analysis-0.1.3.dist-info/entry_points.txt
optimize_device_analysis-0.1.3.dist-info/top_level.txt
optimize_device_analysis-0.1.3.dist-info/RECORD
