Metadata-Version: 2.1
Name: optimize_device_analysis
Version: 0.1.3
Author: Akhilesh Keerthi
Author-email: akeerthi@gmu.edu
Maintainer: Akhilesh Keerthi, Sai Kumar Aili
Maintainer-email: akeerthi@gmu.edu, saili@gmu.edu
Requires-Dist: psutil
Requires-Dist: matplotlib
Requires-Dist: requests
Requires-Dist: pandas
